azure/__init__.py
azure/cli/__init__.py
azure/cli/command_modules/__init__.py
azure/cli/command_modules/backup/__init__.py
azure/cli/command_modules/backup/_client_factory.py
azure/cli/command_modules/backup/_format.py
azure/cli/command_modules/backup/_help.py
azure/cli/command_modules/backup/_params.py
azure/cli/command_modules/backup/_validators.py
azure/cli/command_modules/backup/commands.py
azure/cli/command_modules/backup/custom.py
opal_azure_cli_backup-1.2.7.dist-info/METADATA
opal_azure_cli_backup-1.2.7.dist-info/WHEEL
opal_azure_cli_backup-1.2.7.dist-info/top_level.txt
opal_azure_cli_backup-1.2.7.dist-info/RECORD
